orca_mcp_server.py
orca_mcp_server-1.0.2.dist-info/METADATA
orca_mcp_server-1.0.2.dist-info/WHEEL
orca_mcp_server-1.0.2.dist-info/entry_points.txt
orca_mcp_server-1.0.2.dist-info/RECORD
