Metadata-Version: 2.4
Name: orca-mcp-server
Version: 1.0.2
Summary: Orca Security MCP Server
Author: Orca Security
Maintainer-email: Irad Aharoni <irad.aharoni@orca.security>
License: MIT
Keywords: mcp,orca,security,server
Classifier: Development Status :: 3 - Alpha
Classifier: Intended Audience :: Developers
Classifier: License :: OSI Approved :: MIT License
Classifier: Programming Language :: Python :: 3.10
Requires-Python: >=3.11
Requires-Dist: fastmcp>=2.3.4
Requires-Dist: httpx>=0.28.1
